{
	"saldos_cxc": [
		{
      "cliente_id": 1,
      "cliente_nombre": "Cliente 1",
      "saldo_id": 1,
			"documento": "Documento 1",
			"fecha_documento": "2021-11-15 19:48:12",
			"fecha_vencimiento": "2021-11-15 19:48:12",
			"estado": "Pendiente",
			"locale":"en-US",
			"currency":"USD",
			"currency_code":"$",
			"saldo_inicial": "1000.00",
			"saldo_abonado": "100.00",
			"saldo_final": "900.00",
			"dias_credito": "30",
			"mora": 0
		},
    {
			"cliente_id": 2,
			"cliente_nombre": "Cliente 2",
      "saldo_id": 2,
			"documento": "Documento 2",
			"fecha_documento": "2021-11-15 19:48:12",
			"fecha_vencimiento": "2021-11-15 19:48:12",
			"estado": "Pendiente",
			"locale":"es-HN",
			"currency":"HNL",
			"currency_code":"L",
			"saldo_inicial": "1000.00",
			"saldo_abonado": "200.00",
			"saldo_final": "800.00",
			"dias_credito": "30",
			"mora": 30
		},
    {
			"cliente_id": 3,
			"cliente_nombre": "Cliente 3",
      "saldo_id": 3,
			"documento": "Documento 3",
			"fecha_documento": "2021-11-15 19:48:12",
			"fecha_vencimiento": "2021-11-15 19:48:12",
			"estado": "Pendiente",
			"locale":"en-US",
			"currency":"USD",
			"currency_code":"$",
			"saldo_inicial": "1000.00",
			"saldo_abonado": "300.00",
			"saldo_final": "700.00",
			"dias_credito": "30",
			"mora": 60
		},
    {
			"cliente_id": 4,
			"cliente_nombre": "Cliente 4",
			"saldo_id": 4,
    	"documento": "Documento 4",
			"fecha_documento": "2021-11-15 19:48:12",
			"fecha_vencimiento": "2021-11-15 19:48:12",
			"estado": "Pendiente",
			"locale":"en-US",
			"currency":"USD",
			"currency_code":"$",
			"saldo_inicial": "1000.00",
			"saldo_abonado": "400.00",
			"saldo_final": "600.00",
			"dias_credito": "30",
			"mora": 90
		},
    {
			"cliente_id":5,
			"cliente_nombre": "Cliente5",
      "saldo_id": 5,
			"documento": "Documento 5",
			"fecha_documento": "2021-11-15 19:48:12",
			"fecha_vencimiento": "2021-11-15 19:48:12",
			"estado": "Pendiente",
			"locale":"en-US",
			"currency":"USD",
			"currency_code":"$",
			"saldo_inicial": "1000.00",
			"saldo_abonado": "500.00",
			"saldo_final": "500.00",
			"dias_credito": "30",
			"mora": 120
		},
    {
			"cliente_id":6,
			"cliente_nombre": "Cliente6",
      "saldo_id": 6,
			"documento": "Documento 6",
			"fecha_documento": "2021-11-15 19:48:12",
			"fecha_vencimiento": "2021-11-15 19:48:12",
			"estado": "Pendiente",
			"locale":"en-US",
			"currency":"USD",
			"currency_code":"$",
			"saldo_inicial": "1000.00",
			"saldo_abonado": "500.00",
			"saldo_final": "500.00",
			"dias_credito": "30",
			"mora": 120
		},
    {
			"cliente_id":7,
			"cliente_nombre": "Cliente7",
      "saldo_id": 7,
			"documento": "Documento 7",
			"fecha_documento": "2021-11-15 19:48:12",
			"fecha_vencimiento": "2021-11-15 19:48:12",
			"estado": "Pendiente",
			"locale":"en-US",
			"currency":"USD",
			"currency_code":"$",
			"saldo_inicial": "1000.00",
			"saldo_abonado": "500.00",
			"saldo_final": "500.00",
			"dias_credito": "30",
			"mora": 120
		},
    {
			"cliente_id":8,
			"cliente_nombre": "Cliente8",
      "saldo_id": 8,
			"documento": "Documento 8",
			"fecha_documento": "2021-11-15 19:48:12",
			"fecha_vencimiento": "2021-11-15 19:48:12",
			"estado": "Pendiente",
			"locale":"en-US",
			"currency":"USD",
			"currency_code":"$",
			"saldo_inicial": "1000.00",
			"saldo_abonado": "500.00",
			"saldo_final": "500.00",
			"dias_credito": "30",
			"mora": 120
		},
    {
			"cliente_id":9,
			"cliente_nombre": "Cliente9",
      "saldo_id": 9,
			"documento": "Documento 9",
			"fecha_documento": "2021-11-15 19:48:12",
			"fecha_vencimiento": "2021-11-15 19:48:12",
			"estado": "Pendiente",
			"locale":"en-US",
			"currency":"USD",
			"currency_code":"$",
			"saldo_inicial": "1000.00",
			"saldo_abonado": "500.00",
			"saldo_final": "500.00",
			"dias_credito": "30",
			"mora": 120
		},
    {
			"cliente_id":10,
			"cliente_nombre": "Cliente10",
      "saldo_id": 10,
			"documento": "Documento 10",
			"fecha_documento": "2021-11-15 19:48:12",
			"fecha_vencimiento": "2021-11-15 19:48:12",
			"estado": "Pendiente",
			"locale":"en-US",
			"currency":"USD",
			"currency_code":"$",
			"saldo_inicial": "1000.00",
			"saldo_abonado": "500.00",
			"saldo_final": "500.00",
			"dias_credito": "30",
			"mora": 120
		},
    {
			"cliente_id":11,
			"cliente_nombre": "Cliente11",
      "saldo_id": 11,
			"documento": "Documento 11",
			"fecha_documento": "2021-11-15 19:48:12",
			"fecha_vencimiento": "2021-11-15 19:48:12",
			"estado": "Pendiente",
			"locale":"en-US",
			"currency":"USD",
			"currency_code":"$",
			"saldo_inicial": "1000.00",
			"saldo_abonado": "500.00",
			"saldo_final": "500.00",
			"dias_credito": "30",
			"mora": 120
		},
    {
			"cliente_id":12,
			"cliente_nombre": "Cliente12",
      "saldo_id": 12,
			"documento": "Documento 12",
			"fecha_documento": "2021-11-15 19:48:12",
			"fecha_vencimiento": "2021-11-15 19:48:12",
			"estado": "Pendiente",
			"locale":"en-US",
			"currency":"USD",
			"currency_code":"$",
			"saldo_inicial": "1000.00",
			"saldo_abonado": "500.00",
			"saldo_final": "500.00",
			"dias_credito": "30",
			"mora": 120
		},
    {
			"cliente_id":13,
			"cliente_nombre": "Cliente13",
      "saldo_id": 13,
			"documento": "Documento 13",
			"fecha_documento": "2021-11-15 19:48:12",
			"fecha_vencimiento": "2021-11-15 19:48:12",
			"estado": "Pendiente",
			"locale":"en-US",
			"currency":"USD",
			"currency_code":"$",
			"saldo_inicial": "1000.00",
			"saldo_abonado": "500.00",
			"saldo_final": "500.00",
			"dias_credito": "30",
			"mora": 120
		},
    {
			"cliente_id":14,
			"cliente_nombre": "Cliente14",
      "saldo_id": 14,
			"documento": "Documento 14",
			"fecha_documento": "2021-11-15 19:48:12",
			"fecha_vencimiento": "2021-11-15 19:48:12",
			"estado": "Pendiente",
			"locale":"en-US",
			"currency":"USD",
			"currency_code":"$",
			"saldo_inicial": "1000.00",
			"saldo_abonado": "500.00",
			"saldo_final": "500.00",
			"dias_credito": "30",
			"mora": 120
		},
    {
			"cliente_id":15,
			"cliente_nombre": "Cliente15",
      "saldo_id": 15,
			"documento": "Documento 15",
			"fecha_documento": "2021-11-15 19:48:12",
			"fecha_vencimiento": "2021-11-15 19:48:12",
			"estado": "Pendiente",
			"locale":"en-US",
			"currency":"USD",
			"currency_code":"$",
			"saldo_inicial": "1000.00",
			"saldo_abonado": "500.00",
			"saldo_final": "500.00",
			"dias_credito": "30",
			"mora": 120
		},
    {
			"cliente_id":16,
			"cliente_nombre": "Cliente16",
      "saldo_id": 16,
			"documento": "Documento 16",
			"fecha_documento": "2021-11-15 19:48:12",
			"fecha_vencimiento": "2021-11-15 19:48:12",
			"estado": "Pendiente",
			"locale":"en-US",
			"currency":"USD",
			"currency_code":"$",
			"saldo_inicial": "1000.00",
			"saldo_abonado": "500.00",
			"saldo_final": "500.00",
			"dias_credito": "30",
			"mora": 120
		},
    {
			"cliente_id":17,
			"cliente_nombre": "Cliente17",
      "saldo_id": 17,
			"documento": "Documento 17",
			"fecha_documento": "2021-11-15 19:48:12",
			"fecha_vencimiento": "2021-11-15 19:48:12",
			"estado": "Pendiente",
			"locale":"en-US",
			"currency":"USD",
			"currency_code":"$",
			"saldo_inicial": "1000.00",
			"saldo_abonado": "500.00",
			"saldo_final": "500.00",
			"dias_credito": "30",
			"mora": 120
		},
    {
			"cliente_id":18,
			"cliente_nombre": "Cliente18",
      "saldo_id": 18,
			"documento": "Documento 18",
			"fecha_documento": "2021-11-15 19:48:12",
			"fecha_vencimiento": "2021-11-15 19:48:12",
			"estado": "Pendiente",
			"locale":"en-US",
			"currency":"USD",
			"currency_code":"$",
			"saldo_inicial": "1000.00",
			"saldo_abonado": "500.00",
			"saldo_final": "500.00",
			"dias_credito": "30",
			"mora": 120
		},
    {
			"cliente_id":19,
			"cliente_nombre": "Cliente19",
      "saldo_id": 19,
			"documento": "Documento 19",
			"fecha_documento": "2021-11-15 19:48:12",
			"fecha_vencimiento": "2021-11-15 19:48:12",
			"estado": "Pendiente",
			"locale":"en-US",
			"currency":"USD",
			"currency_code":"$",
			"saldo_inicial": "1000.00",
			"saldo_abonado": "500.00",
			"saldo_final": "500.00",
			"dias_credito": "30",
			"mora": 120
		},
    {
			"cliente_id":20,
			"cliente_nombre": "Cliente20",
      "saldo_id": 20,
			"documento": "Documento 20",
			"fecha_documento": "2021-11-15 19:48:12",
			"fecha_vencimiento": "2021-11-15 19:48:12",
			"estado": "Pendiente",
			"locale":"en-US",
			"currency":"USD",
			"currency_code":"$",
			"saldo_inicial": "1000.00",
			"saldo_abonado": "500.00",
			"saldo_final": "500.00",
			"dias_credito": "30",
			"mora": 120
		},
    {
			"cliente_id":21,
			"cliente_nombre": "Cliente21",
      "saldo_id": 21,
			"documento": "Documento 21",
			"fecha_documento": "2021-11-15 19:48:12",
			"fecha_vencimiento": "2021-11-15 19:48:12",
			"estado": "Pendiente",
			"locale":"en-US",
			"currency":"USD",
			"currency_code":"$",
			"saldo_inicial": "1000.00",
			"saldo_abonado": "500.00",
			"saldo_final": "500.00",
			"dias_credito": "30",
			"mora": 120
		},
    {
			"cliente_id":22,
			"cliente_nombre": "Cliente22",
      "saldo_id": 22,
			"documento": "Documento 22",
			"fecha_documento": "2021-11-15 19:48:12",
			"fecha_vencimiento": "2021-11-15 19:48:12",
			"estado": "Pendiente",
			"locale":"en-US",
			"currency":"USD",
			"currency_code":"$",
			"saldo_inicial": "1000.00",
			"saldo_abonado": "500.00",
			"saldo_final": "500.00",
			"dias_credito": "30",
			"mora": 120
		},
    {
			"cliente_id":23,
			"cliente_nombre": "Cliente23",
      "saldo_id": 23,
			"documento": "Documento 23",
			"fecha_documento": "2021-11-15 19:48:12",
			"fecha_vencimiento": "2021-11-15 19:48:12",
			"estado": "Pendiente",
			"locale":"en-US",
			"currency":"USD",
			"currency_code":"$",
			"saldo_inicial": "1000.00",
			"saldo_abonado": "500.00",
			"saldo_final": "500.00",
			"dias_credito": "30",
			"mora": 120
		},
    {
			"cliente_id":24,
			"cliente_nombre": "Cliente24",
      "saldo_id": 24,
			"documento": "Documento 24",
			"fecha_documento": "2021-11-15 19:48:12",
			"fecha_vencimiento": "2021-11-15 19:48:12",
			"estado": "Pendiente",
			"locale":"en-US",
			"currency":"USD",
			"currency_code":"$",
			"saldo_inicial": "1000.00",
			"saldo_abonado": "500.00",
			"saldo_final": "500.00",
			"dias_credito": "30",
			"mora": 120
		},
    {
			"cliente_id":25,
			"cliente_nombre": "Cliente25",
      "saldo_id": 25,
			"documento": "Documento 25",
			"fecha_documento": "2021-11-15 19:48:12",
			"fecha_vencimiento": "2021-11-15 19:48:12",
			"estado": "Pendiente",
			"locale":"en-US",
			"currency":"USD",
			"currency_code":"$",
			"saldo_inicial": "1000.00",
			"saldo_abonado": "500.00",
			"saldo_final": "500.00",
			"dias_credito": "30",
			"mora": 120
		}
	],
	"paginacionResultados": [
		{
			"length": 11,
			"pageIndex": 0,
			"pageSize": 10,
			"previousPageIndex": 0
		}
	]
}